neurobench/__init__.py
neurobench/benchmarks/__init__.py
neurobench/benchmarks/benchmark.py
neurobench/blocks/__init__.py
neurobench/blocks/activation.py
neurobench/blocks/layer.py
neurobench/datasets/MSWC_IncrementalLoader.py
neurobench/datasets/MSWC_dataset.py
neurobench/datasets/WISDM.py
neurobench/datasets/__init__.py
neurobench/datasets/dataset.py
neurobench/datasets/mackey_glass.py
neurobench/datasets/megapixel_automotive.py
neurobench/datasets/primate_reaching.py
neurobench/datasets/speech_commands.py
neurobench/datasets/utils.py
neurobench/hooks/__init__.py
neurobench/hooks/layer.py
neurobench/hooks/neuron.py
neurobench/metrics/__init__.py
neurobench/metrics/abstract/__init__.py
neurobench/metrics/abstract/static_metric.py
neurobench/metrics/abstract/workload_metric.py
neurobench/metrics/manager/__init__.py
neurobench/metrics/manager/static_manager.py
neurobench/metrics/manager/workload_manager.py
neurobench/metrics/static/__init__.py
neurobench/metrics/static/connection_sparsity.py
neurobench/metrics/static/footprint.py
neurobench/metrics/static/parameter_count.py
neurobench/metrics/utils/__init__.py
neurobench/metrics/utils/decorators/__init__.py
neurobench/metrics/utils/decorators/check_shape.py
neurobench/metrics/utils/layers/__init__.py
neurobench/metrics/utils/layers/binary_copy.py
neurobench/metrics/utils/layers/input.py
neurobench/metrics/utils/layers/macs.py
neurobench/metrics/utils/utils.py
neurobench/metrics/workload/__init__.py
neurobench/metrics/workload/activation_sparsity.py
neurobench/metrics/workload/activation_sparsity_by_layer.py
neurobench/metrics/workload/classification_accuracy.py
neurobench/metrics/workload/coco_map.py
neurobench/metrics/workload/membrane_updates.py
neurobench/metrics/workload/mse.py
neurobench/metrics/workload/neuron_operations.py
neurobench/metrics/workload/r2.py
neurobench/metrics/workload/smape.py
neurobench/metrics/workload/synaptic_operations.py
neurobench/models/__init__.py
neurobench/models/neurobench_model.py
neurobench-2.2.0.dist-info/METADATA
neurobench-2.2.0.dist-info/WHEEL
neurobench-2.2.0.dist-info/licenses/LICENSE
neurobench-2.2.0.dist-info/licenses/NOTICE
neurobench-2.2.0.dist-info/RECORD
