Metadata-Version: 2.4
Name: neurobench
Version: 2.2.0
Summary: Collaborative, Fair, and Representative Benchmarks for Neuromorphic Computing
License-File: LICENSE
License-File: NOTICE
Author: NeuroBench Team
Author-email: neurobench@googlegroups.com
Requires-Python: >=3.10,<4.0
Classifier: Programming Language :: Python :: 3
Classifier: Programming Language :: Python :: 3.10
Classifier: Programming Language :: Python :: 3.11
Classifier: Programming Language :: Python :: 3.12
Classifier: Programming Language :: Python :: 3.13
Classifier: Programming Language :: Python :: 3.14
Provides-Extra: mackey-glass
Provides-Extra: nehar
Requires-Dist: gdown (>=4.7.1,<5.0.0) ; extra == "nehar"
Requires-Dist: jitcdde (>=1.8.1,<2.0.0) ; extra == "mackey-glass"
Requires-Dist: llvmlite (>=0.40.1)
Requires-Dist: numba (>=0.57.1)
Requires-Dist: numpy (>=1.24.3) ; python_version < "3.12"
Requires-Dist: numpy (>=1.25.0) ; python_version >= "3.12"
Requires-Dist: pytorch-lightning (>=1.4.0,<2.0.0) ; extra == "nehar"
Requires-Dist: snntorch (>=0.7.0)
Requires-Dist: tonic (>=1.4.0,<2.0.0)
Requires-Dist: torch (>=2.0.1)
Requires-Dist: torchaudio (>=2.0.2)
Requires-Dist: tqdm (>=4.63.3,<5.0.0)
